[
  {
    "eventType": "EventP",
    "eventDescription": {
      "text": "classified as either moderately or severely food insecure",
      "start": 332,
      "end": 389
    },
    "modifier": {
      "text": "more than",
      "start": 295,
      "end": 304
    },
    "quantity": {
      "text": "50%",
      "start": 305,
      "end": 308
    },
    "unit": {
      "text": "households",
      "start": 316,
      "end": 326
    }
  },
  {
    "eventType": "EventP",
    "eventDescription": {
      "text": "either moderately food insecure or severely food insecure",
      "start": null,
      "end": null
    },
    "quantity": {
      "text": "87%",
      "start": 461,
      "end": 464
    },
    "unit": {
      "text": "households",
      "start": 468,
      "end": 478
    }
  },
  {
    "eventType": "EventP",
    "eventDescription": {
      "text": "moderately food insecure",
      "start": 486,
      "end": 510
    },
    "quantity": {
      "text": "49%",
      "start": 512,
      "end": 515
    },
    "unit": {
      "text": "households",
      "start": null,
      "end": null
    }
  },
  {
    "eventType": "EventP",
    "eventDescription": {
      "text": "severely food insecure",
      "start": 520,
      "end": 542
    },
    "quantity": {
      "text": "38%",
      "start": 544,
      "end": 547
    },
    "unit": {
      "text": "households",
      "start": null,
      "end": null
    }
  },
  {
    "eventType": "EventP",
    "eventDescription": {
      "text": "food insecure",
      "start": null,
      "end": null
    },
    "quantity": {
      "text": "74%",
      "start": 627,
      "end": 630
    },
    "unit": {
      "text": "households",
      "start": null,
      "end": null
    }
  },
  {
    "eventType": "EventP",
    "eventDescription": {
      "text": "food insecure",
      "start": null,
      "end": null
    },
    "quantity": {
      "text": "78",
      "start": 657,
      "end": 659
    },
    "unit": {
      "text": "households",
      "start": null,
      "end": null
    }
  },
  {
    "eventType": "EventP",
    "eventDescription": {
      "text": "food insecure",
      "start": null,
      "end": null
    },
    "quantity": {
      "text": "82%",
      "start": 682,
      "end": 685
    },
    "unit": {
      "text": "households",
      "start": null,
      "end": null
    }
  },
  {
    "eventType": "EventP",
    "eventDescription": {
      "text": "food insecure",
      "start": null,
      "end": null
    },
    "quantity": {
      "text": "70",
      "start": 713,
      "end": 715
    },
    "unit": {
      "text": "households",
      "start": null,
      "end": null
    }
  },
  {
    "eventType": "EventP",
    "eventDescription": {
      "text": "food insecure",
      "start": null,
      "end": null
    },
    "quantity": {
      "text": "69%",
      "start": 729,
      "end": 732
    },
    "unit": {
      "text": "households",
      "start": null,
      "end": null
    }
  }
]