[
  {
    "eventType": "EventP",
    "eventDescription": {
      "text": "screened",
      "start": null,
      "end": null
    },
    "quantity": {
      "text": "115",
      "start": 77,
      "end": 80
    },
    "unit": {
      "text": "children",
      "start": 81,
      "end": 89
    }
  },
  {
    "eventType": "EventP",
    "eventDescription": {
      "text": "age range of children screened",
      "start": null,
      "end": null
    },
    "quantity": {
      "text": "6-59",
      "start": 90,
      "end": 94
    },
    "unit": {
      "text": "months of age",
      "start": 95,
      "end": 108
    }
  },
  {
    "eventType": "EventP",
    "eventDescription": {
      "text": "at risk of acute malnutrition",
      "start": 290,
      "end": 319
    },
    "quantity": {
      "text": "eight",
      "start": 245,
      "end": 250
    },
    "unit": {
      "text": "children",
      "start": 251,
      "end": 259
    }
  },
  {
    "eventType": "EventP",
    "eventDescription": {
      "text": "at risk of acute malnutrition",
      "start": null,
      "end": null
    },
    "quantity": {
      "text": "7 percent",
      "start": 261,
      "end": 270
    },
    "unit": {
      "text": "of the total",
      "start": 271,
      "end": 283
    }
  }
]