[
  {
    "eventType": "EventA",
    "eventDescription": {
      "text": "WASH facilities provided",
      "start": null,
      "end": null
    },
    "quantity": {
      "text": "74 per cent",
      "start": 131,
      "end": 142
    },
    "unit": {
      "text": "sites",
      "start": 146,
      "end": 151
    }
  },
  {
    "eventType": "EventA",
    "eventDescription": {
      "text": "increase in WASH facilities provided",
      "start": null,
      "end": null
    },
    "quantity": {
      "text": "1%",
      "start": 189,
      "end": 191
    },
    "unit": {
      "text": "sites",
      "start": 265,
      "end": 270
    }
  },
  {
    "eventType": "EventA",
    "eventDescription": {
      "text": "sites with no WASH facilities",
      "start": null,
      "end": null
    },
    "quantity": {
      "text": "26 per cent",
      "start": 250,
      "end": 261
    },
    "unit": {
      "text": "sites",
      "start": null,
      "end": null
    }
  },
  {
    "eventType": "EventA",
    "eventDescription": {
      "text": "decrease in sites with no WASH facilities",
      "start": null,
      "end": null
    },
    "quantity": {
      "text": "1%",
      "start": 280,
      "end": 282
    },
    "unit": {
      "text": "sites",
      "start": null,
      "end": null
    }
  },
  {
    "eventType": "EventA",
    "eventDescription": {
      "text": "locations with hand pumps",
      "start": null,
      "end": null
    },
    "quantity": {
      "text": "30 per cent",
      "start": 351,
      "end": 362
    },
    "unit": {
      "text": "locations",
      "start": 366,
      "end": 375
    }
  },
  {
    "eventType": "EventA",
    "eventDescription": {
      "text": "locations with communal boreholes",
      "start": null,
      "end": null
    },
    "quantity": {
      "text": "30 per cent",
      "start": 488,
      "end": 499
    },
    "unit": {
      "text": "locations",
      "start": 503,
      "end": 512
    }
  },
  {
    "eventType": "EventA",
    "eventDescription": {
      "text": "increase in locations with communal boreholes",
      "start": null,
      "end": null
    },
    "quantity": {
      "text": "1%",
      "start": 520,
      "end": 522
    },
    "unit": {
      "text": "locations",
      "start": 571,
      "end": 580
    }
  },
  {
    "eventType": "EventA",
    "eventDescription": {
      "text": "locations with communal wells",
      "start": null,
      "end": null
    },
    "quantity": {
      "text": "11 per cent",
      "start": 556,
      "end": 567
    },
    "unit": {
      "text": "locations",
      "start": null,
      "end": null
    }
  }
]