[
  {
    "eventType": "EventO",
    "eventDescription": {
      "text": "ranked",
      "start": 59,
      "end": 65
    },
    "quantity": {
      "text": "178",
      "start": null,
      "end": null
    },
    "unit": {
      "text": "countries",
      "start": 83,
      "end": 92
    }
  },
  {
    "eventType": "EventO",
    "eventDescription": {
      "text": "ranked",
      "start": null,
      "end": null
    },
    "quantity": {
      "text": "189",
      "start": 79,
      "end": 82
    },
    "unit": {
      "text": "countries",
      "start": null,
      "end": null
    }
  },
  {
    "eventType": "EventP",
    "eventDescription": {
      "text": "estimated to be living in poverty",
      "start": 183,
      "end": 216
    },
    "modifier": {
      "text": "at least",
      "start": null,
      "end": null
    },
    "quantity": {
      "text": "at least 50 percent",
      "start": null,
      "end": null
    },
    "unit": {
      "text": "of the population",
      "start": 162,
      "end": 179
    }
  },
  {
    "eventType": "EventA",
    "eventDescription": {
      "text": "imported",
      "start": 263,
      "end": 271
    },
    "modifier": {
      "text": "more than",
      "start": 222,
      "end": 231
    },
    "quantity": {
      "text": "more than 90 percent",
      "start": 222,
      "end": 242
    },
    "unit": {
      "text": "of food in Yemen",
      "start": 243,
      "end": 259
    }
  },
  {
    "eventType": "EventO",
    "eventDescription": {
      "text": "present in Yemen",
      "start": null,
      "end": null
    },
    "quantity": {
      "text": "1967",
      "start": 546,
      "end": 550
    },
    "unit": {
      "text": "since",
      "start": 540,
      "end": 545
    }
  }
]