[
  {
    "eventType": "EventP",
    "eventDescription": {
      "text": "safe in Cameroon",
      "start": 42,
      "end": 58
    },
    "quantity": {
      "text": "35,000",
      "start": 13,
      "end": 19
    },
    "unit": {
      "text": "Nigerian refugees",
      "start": 20,
      "end": 37
    }
  },
  {
    "eventType": "EventO",
    "eventDescription": {
      "text": "collected",
      "start": null,
      "end": null
    },
    "quantity": {
      "text": "a few",
      "start": 157,
      "end": 162
    },
    "unit": {
      "text": "personal possessions",
      "start": 163,
      "end": 183
    }
  },
  {
    "eventType": "EventO",
    "eventDescription": {
      "text": "Boko Haram active",
      "start": null,
      "end": null
    },
    "modifier": {
      "text": "over",
      "start": 461,
      "end": 465
    },
    "quantity": {
      "text": "over a decade",
      "start": 461,
      "end": 474
    }
  },
  {
    "eventType": "EventP",
    "eventDescription": {
      "text": "killed",
      "start": 568,
      "end": 574
    },
    "quantity": {
      "text": "Thousands",
      "start": 476,
      "end": 485
    },
    "unit": {
      "text": "people",
      "start": 252,
      "end": 258
    }
  },
  {
    "eventType": "EventP",
    "eventDescription": {
      "text": "livelihoods destroyed",
      "start": null,
      "end": null
    },
    "quantity": {
      "text": "tens of thousands",
      "start": 621,
      "end": 638
    },
    "unit": {
      "text": "others",
      "start": 642,
      "end": 648
    }
  }
]